Metadata-Version: 2.1
Name: realog
Version: 1.2.2
Summary: atria debug is a simple tool to log the data in color, with a level management
Home-page: http://github.com/HeeroYui/realog
Author: Edouard DUPIN
Author-email: yui.heero@gmail.com
License: MPL-2
Keywords: log logs debug print console
Platform: UNKNOWN
Classifier: Development Status :: 5 - Production/Stable
Classifier: License :: OSI Approved :: Mozilla Public License 2.0 (MPL 2.0)
Classifier: Programming Language :: Python
Classifier: Topic :: Software Development :: Libraries :: Python Modules
